bezalel/__init__.py
bezalel/impl/BufferingIterator.py
bezalel/impl/CursorApiIterator.py
bezalel/impl/PaginatedApiIterator.py
bezalel/impl/__init__.py
bezalel/impl/dict_utils.py
bezalel/impl/normalize_dicts.py
bezalel/impl/normalize_with_prototype.py
bezalel/impl/prepare_job.py
bezalel-0.0.21.dist-info/licenses/LICENSE
bezalel-0.0.21.dist-info/METADATA
bezalel-0.0.21.dist-info/WHEEL
bezalel-0.0.21.dist-info/top_level.txt
bezalel-0.0.21.dist-info/RECORD
