Metadata-Version: 2.4
Name: bezalel
Version: 0.0.21
Summary: A library for ingesting data provided by paginated HTTP APIs
Author: bezalelsoft
Project-URL: Source, https://github.com/bezalelsoft/bezalel
Project-URL: Bug-Tracker, https://github.com/bezalelsoft/bezalel/issues
Classifier: Programming Language :: Python :: 3
Classifier: License :: OSI Approved :: MIT License
Classifier: Operating System :: OS Independent
Requires-Python: >=3.6
License-File: LICENSE
Requires-Dist: requests
Provides-Extra: dev
Requires-Dist: fastapi; extra == "dev"
Requires-Dist: uvicorn; extra == "dev"
Requires-Dist: pytest; extra == "dev"
Dynamic: license-file
